{"cameraMode":{"drawMode":0,"name":"Shaded","section":"Shading Mode"},"sceneLighting":true,"audioPlay":false,"sceneViewState":{"showFog":true,"showMaterialUpdate":false,"showSkybox":true,"showFlares":true,"showImageEffects":true,"showParticleSystems":true},"in2DMode":false,"pivot":{"x":-0.6559090614318848,"y":5.48527717590332,"z":-2.093959331512451},"rotation":{"x":-0.45348188281059267,"y":-0.2706092894077301,"z":0.1467178463935852,"w":-0.8364256024360657},"size":10.001904487609864,"orthographic":false}